easemysql/ListORM.py
easemysql/__init__.py
easemysql/main.py
easemysql/session.py
easemysql/tests.py
easemysql/utils.py
easemysql-1.1.3.dist-info/METADATA
easemysql-1.1.3.dist-info/WHEEL
easemysql-1.1.3.dist-info/top_level.txt
easemysql-1.1.3.dist-info/RECORD
