Metadata-Version: 2.4
Name: easemysql
Version: 1.1.3
Summary: 简单易用的 mysql 封装
Home-page: https://gitee.com/jaifire/easemysql
Author: jaifire
Author-email: boydearea@163.com
Classifier: Programming Language :: Python :: 3
Classifier: License :: OSI Approved :: MIT License
Classifier: Operating System :: OS Independent
Requires-Python: >=3.6
Dynamic: author
Dynamic: author-email
Dynamic: classifier
Dynamic: description
Dynamic: description-content-type
Dynamic: home-page
Dynamic: requires-python
Dynamic: summary
